plan2eplus/__init__.py
plan2eplus/main.py
plan2eplus/airflow_network/airboundary.py
plan2eplus/airflow_network/creator.py
plan2eplus/airflow_network/logic.py
plan2eplus/airflow_network/modifiers.py
plan2eplus/analysis/analysis_air_boundary.py
plan2eplus/analysis/cp_eq.py
plan2eplus/analysis/dataframes.py
plan2eplus/analysis/dataframes2.py
plan2eplus/analysis/ep_wind_cp.cpp
plan2eplus/analysis/helpers.py
plan2eplus/analysis/materials_compare.py
plan2eplus/analysis/plan_details.py
plan2eplus/analysis/plot_helpers.py
plan2eplus/analysis/plot_subsurfaces.py
plan2eplus/analysis/pressure_on_network.py
plan2eplus/analysis/result_names.json
plan2eplus/analysis/time_plots.py
plan2eplus/analysis/volumes.py
plan2eplus/analysis2/all_cases_v_time.py
plan2eplus/case_edits/__init__.py
plan2eplus/case_edits/defaults.py
plan2eplus/case_edits/epcase.py
plan2eplus/case_edits/ezcase.py
plan2eplus/constructions/constructions.py
plan2eplus/constructions/materials.py
plan2eplus/constructions/organize.py
plan2eplus/constructions/unified_constructions.py
plan2eplus/experiments/comparisons.py
plan2eplus/experiments/dynamic_door_sched.py
plan2eplus/experiments/name_splits.py
plan2eplus/experiments/retrieve.py
plan2eplus/experiments/scatter.py
plan2eplus/helpers/dates.py
plan2eplus/helpers/ep_geom_helpers.py
plan2eplus/helpers/ep_helpers.py
plan2eplus/helpers/geometry_interfaces.py
plan2eplus/helpers/helpers.py
plan2eplus/helpers/output_requests.py
plan2eplus/helpers/plot_colors.py
plan2eplus/helpers/plots.py
plan2eplus/helpers/read_sql.py
plan2eplus/helpers/save_details
plan2eplus/helpers/variable_interfaces.py
plan2eplus/helpers/variables.py
plan2eplus/network/cardinal_positions.py
plan2eplus/network/network.py
plan2eplus/network/visuals.py
plan2eplus/plan/graph_to_subsurfaces.py
plan2eplus/plan/helpers.py
plan2eplus/plan/interfaces.py
plan2eplus/plan/plan_to_eppy.py
plan2eplus/setup/data_wrangle.py
plan2eplus/setup/data_wrangle2.py
plan2eplus/setup/interfaces.py
plan2eplus-0.1.0.dist-info/METADATA
plan2eplus-0.1.0.dist-info/WHEEL
plan2eplus-0.1.0.dist-info/entry_points.txt
plan2eplus-0.1.0.dist-info/RECORD
