Metadata-Version: 2.4
Name: plan2eplus
Version: 0.1.0
Summary: Add your description here
Author-email: Juliet Nwagwu Ume-Ezeoke <jnwagwu@stanford.edu>
Requires-Python: >=3.13
Requires-Dist: eppy>=0.5.63
Requires-Dist: geomeppy>=0.11.8
Requires-Dist: ladybug-core>=0.43.22
Requires-Dist: ladybug>=0.0.2
Requires-Dist: plotly>=5.24.1
Requires-Dist: polars>=1.20.0
Requires-Dist: rich>=13.9.4
